Workbook

Sheet Debt Equity
A1: Nebius (NBIS): 5 GW build funding model, 2027–2030
A2: in Billions unless specified
B3: Jun'26 A | C3: 2027 | D3: 2028 | E3: 2029 | F3: 2030 | G3: 2027–30
A4: Active GW | B4: 0.4 | C4: =B4+C5 -> 1.55 | D4: =C4+D5 -> 2.7 | E4: =D4+E5 -> 3.85 | F4: =E4+F5 -> 5 | G4: =F4 -> 5
A5: GW added in year | C5: 1.15 | D5: 1.15 | E5: 1.15 | F5: 1.15 | G5: =SUM(C5:F5) -> 4.6
A6: ARR (= GW × ARR per MW) | B6: =B4*B7 -> 8 | C6: =C4*C7 -> 34.1 | D6: =D4*D7 -> 67.5 | E6: =E4*E7 -> 96.25 | F6: =F4*F7 -> 125 | G6: =F6 -> 125
A7: ARR per MW ($M) — floor | B7: 20 | C7: 22 | D7: 25 | E7: 25 | F7: 25
A8: Recognized revenue (= avg of opening/closing ARR) | C8: =(B6+C6)/2 -> 21.05 | D8: =(C6+D6)/2 -> 50.8 | E8: =(D6+E6)/2 -> 81.875 | F8: =(E6+F6)/2 -> 110.625 | G8: =SUM(C8:F8) -> 264.35
A9: EBITDA (= revenue × margin) | C9: =C8*C10 -> 10.525 | D9: =D8*D10 -> 25.4 | E9: =E8*E10 -> 40.9375 | F9: =F8*F10 -> 55.3125 | G9: =SUM(C9:F9) -> 132.175
A10: EBITDA margin (% of revenue) | C10: 0.5 | D10: 0.5 | E10: 0.5 | F10: 0.5 | G10: =IF(G8=0,0,G9/G8) -> 0.5
A11: Capex (= total program × GW added share) | C11: =$B$66*C5/$G$5 -> 67.5 | D11: =$B$66*D5/$G$5 -> 67.5 | E11: =$B$66*E5/$G$5 -> 67.5 | F11: =$B$66*F5/$G$5 -> 67.5 | G11: =SUM(C11:F11) -> 270
A12: Prepayments (= capex × rate) | C12: =C11*$B$65 -> 30.375 | D12: =D11*$B$65 -> 30.375 | E12: =E11*$B$65 -> 30.375 | F12: =F11*$B$65 -> 30.375 | G12: =SUM(C12:F12) -> 121.5
A13: Operating cash available (= EBITDA × conversion) | C13: =C9*C14 -> 7.3675 | D13: =D9*D14 -> 19.558 | E13: =E9*E14 -> 32.340625 | F13: =F9*F14 -> 44.25 | G13: =SUM(C13:F13) -> 103.51613
A14: Cash conversion (% of EBITDA; rest funds expenses) | C14: 0.7 | D14: 0.77 | E14: 0.79 | F14: 0.8 | G14: =IF(G9=0,0,G13/G9) -> 0.78317477
A15: Less: cash interest (= total interest, row 39) | C15: =-C40 -> -0.085457 | D15: =-D40 -> -1.4027945 | E15: =-E40 -> -2.6978195 | F15: =-F40 -> -3.9695382 | G15: =SUM(C15:F15) -> -8.1556092
A16: Operating cash available, net of interest | C16: =C13+C15 -> 7.282043 | D16: =D13+D15 -> 18.155206 | E16: =E13+E15 -> 29.642806 | F16: =F13+F15 -> 40.280462 | G16: =SUM(C16:F16) -> 95.360516
A17: EBITDA applied to capex (= 15% of EBITDA) | C17: =MIN($B$67*C9,C16) -> 1.57875 | D17: =MIN($B$67*D9,D16) -> 3.81 | E17: =MIN($B$67*E9,E16) -> 6.140625 | F17: =MIN($B$67*F9,F16) -> 8.296875 | G17: =SUM(C17:F17) -> 19.82625
A18: Secured / asset-backed debt (drawn first, to cap) | C18: =MAX(0,MIN(C11-C12-C17-C20,C11*$B$68)) -> 16.875 | D18: =MAX(0,MIN(D11-D12-D17-D20,D11*$B$68)) -> 16.875 | E18: =MAX(0,MIN(E11-E12-E17-E20,E11*$B$68)) -> 16.875 | F18: =MAX(0,MIN(F11-F12-F17-F20,F11*$B$68)) -> 15.328125 | G18: =SUM(C18:F18) -> 65.953125
A19: Convertible notes (= residual debt need) | C19: =MAX(0,C11-C12-C17-C20-C18) -> 5.17125 | D19: =MAX(0,D11-D12-D17-D20-D18) -> 2.94 | E19: =MAX(0,E11-E12-E17-E20-E18) -> 0.609375 | F19: =MAX(0,F11-F12-F17-F20-F18) -> 0 | G19: =SUM(C19:F19) -> 8.720625
A20: Straight equity (= equity slice of capex) | C20: =$B$64*C11 -> 13.5 | D20: =$B$64*D11 -> 13.5 | E20: =$B$64*E11 -> 13.5 | F20: =$B$64*F11 -> 13.5 | G20: =SUM(C20:F20) -> 54
A21: Funding surplus to cash (= sources − capex) | C21: =C12+C17+C18+C19+C20-C11 -> 0 | D21: =D12+D17+D18+D19+D20-D11 -> 0 | E21: =E12+E17+E18+E19+E20-E11 -> 0 | F21: =F12+F17+F18+F19+F20-F11 -> 0 | G21: =SUM(C21:F21) -> 0
A22: Total debt (= closing debt) | B22: =B82 -> 8.5457 | C22: =C35 -> 30.59195 | D22: =D35 -> 50.40695 | E22: =E35 -> 67.891325 | F22: =F35 -> 83.21945 | G22: =F22 -> 83.21945
A23: Shares (= opening + new issued) | B23: =B85 -> 271.855 | C23: =C51+C53 -> 311.99028 | D23: =D51+D53 -> 331.9794 | E23: =E51+E53 -> 345.21938 | F23: =F51+F53 -> 355.40446 | G23: =F23 -> 355.40446
A24: Self/customer funded (% of capex) | C24: =IF(C11=0,0,(C12+C17)/C11) -> 0.47338889 | D24: =IF(D11=0,0,(D12+D17)/D11) -> 0.50644444 | E24: =IF(E11=0,0,(E12+E17)/E11) -> 0.54097222 | F24: =IF(F11=0,0,(F12+F17)/F11) -> 0.57291667 | G24: =IF(G11=0,0,(G12+G17)/G11) -> 0.52343056
A25: External capital raised (debt + equity) | C25: =C18+C19+C20 -> 35.54625 | D25: =D18+D19+D20 -> 33.315 | E25: =E18+E19+E20 -> 30.984375 | F25: =F18+F19+F20 -> 28.828125 | G25: =SUM(C25:F25) -> 128.67375
A26: Check: total funding − capex (must be 0) | C26: =C12+C17+C25-C11-C21 -> 0 | D26: =D12+D17+D25-D11-D21 -> 0 | E26: =E12+E17+E25-E11-E21 -> 0 | F26: =F12+F17+F25-F11-F21 -> 0 | G26: =G12+G17+G25-G11-G21 -> 0
A27: Memo: operating cash retained (net of interest) | C27: =C16-C17 -> 5.703293 | D27: =D16-D17 -> 14.345206 | E27: =E16-E17 -> 23.502181 | F27: =F16-F17 -> 31.983587 | G27: =SUM(C27:F27) -> 75.534266
A28: Mix: secured | C28: =IF(C$25=0,0,C18/C$25) -> 0.47473362 | D28: =IF(D$25=0,0,D18/D$25) -> 0.50652859 | E28: =IF(E$25=0,0,E18/E$25) -> 0.54462935 | F28: =IF(F$25=0,0,F18/F$25) -> 0.53170732 | G28: =IF(G$25=0,0,G18/G$25) -> 0.51256084
A29: Mix: converts | C29: =IF(C$25=0,0,C19/C$25) -> 0.14547948 | D29: =IF(D$25=0,0,D19/D$25) -> 0.088248537 | E29: =IF(E$25=0,0,E19/E$25) -> 0.019667171 | F29: =IF(F$25=0,0,F19/F$25) -> 0 | G29: =IF(G$25=0,0,G19/G$25) -> 0.067773147
A30: Mix: straight equity | C30: =IF(C$25=0,0,C20/C$25) -> 0.3797869 | D30: =IF(D$25=0,0,D20/D$25) -> 0.40522287 | E30: =IF(E$25=0,0,E20/E$25) -> 0.43570348 | F30: =IF(F$25=0,0,F20/F$25) -> 0.46829268 | G30: =IF(G$25=0,0,G20/G$25) -> 0.41966602
A31: Debt
B32: Jun'26 A | C32: 2027 | D32: 2028 | E32: 2029 | F32: 2030 | G32: 2027–30
A33: Opening debt (January opening) | C33: =B22 -> 8.5457 | D33: =C22 -> 30.59195 | E33: =D22 -> 50.40695 | F33: =E22 -> 67.891325 | G33: =C33 -> 8.5457
A34: + Secured debt + converts issued | C34: =C18+C19 -> 22.04625 | D34: =D18+D19 -> 19.815 | E34: =E18+E19 -> 17.484375 | F34: =F18+F19 -> 15.328125 | G34: =SUM(C34:F34) -> 74.67375
A35: Closing debt (calculated) | C35: =C33+C34 -> 30.59195 | D35: =D33+D34 -> 50.40695 | E35: =E33+E34 -> 67.891325 | F35: =F33+F34 -> 83.21945 | G35: =F35 -> 83.21945
A36: Cumulative secured debt issued | C36: =SUM($C$18:C18) -> 16.875 | D36: =SUM($C$18:D18) -> 33.75 | E36: =SUM($C$18:E18) -> 50.625 | F36: =SUM($C$18:F18) -> 65.953125 | G36: =F36 -> 65.953125
A37: Cumulative new converts issued | C37: =SUM($C$19:C19) -> 5.17125 | D37: =SUM($C$19:D19) -> 8.11125 | E37: =SUM($C$19:E19) -> 8.720625 | F37: =SUM($C$19:F19) -> 8.720625 | G37: =F37 -> 8.720625
A38: Interest on secured debt (= opening secured × rate) | C38: =(B36+$B$83)*$B$70 -> 0 | D38: =(C36+$B$83)*$B$70 -> 1.265625 | E38: =(D36+$B$83)*$B$70 -> 2.53125 | F38: =(E36+$B$83)*$B$70 -> 3.796875 | G38: =SUM(C38:F38) -> 7.59375
A39: Interest on convertible notes (= opening converts × coupon) | C39: =(B37+$B$82-$B$83)*$B$71 -> 0.085457 | D39: =(C37+$B$82-$B$83)*$B$71 -> 0.1371695 | E39: =(D37+$B$82-$B$83)*$B$71 -> 0.1665695 | F39: =(E37+$B$82-$B$83)*$B$71 -> 0.17266325 | G39: =SUM(C39:F39) -> 0.56185925
A40: Total cash interest | C40: =C38+C39 -> 0.085457 | D40: =D38+D39 -> 1.4027945 | E40: =E38+E39 -> 2.6978195 | F40: =F38+F39 -> 3.9695382 | G40: =SUM(C40:F40) -> 8.1556092
A41: Effective blended rate (= interest ÷ opening debt) | C41: =IF(C33=0,0,C40/C33) -> 0.01 | D41: =IF(D33=0,0,D40/D33) -> 0.045855021 | E41: =IF(E33=0,0,E40/E33) -> 0.053520784 | F41: =IF(F33=0,0,F40/F33) -> 0.058469005 | G41: =IF(SUM(C33:F33)=0,0,G40/SUM(C33:F33)) -> 0.051802721
A43: Cash
B44: Jun'26 A | C44: 2027 | D44: 2028 | E44: 2029 | F44: 2030 | G44: 2027–30
A45: Opening cash (January opening) | B45: =$B$84 -> 8.0421 | C45: =$B$84 -> 8.0421 | D45: =C48 -> 13.745393 | E45: =D48 -> 28.090599 | F45: =E48 -> 51.592779 | G45: =C45 -> 8.0421
A46: + Operating cash retained (row 27) | C46: =C27 -> 5.703293 | D46: =D27 -> 14.345206 | E46: =E27 -> 23.502181 | F46: =F27 -> 31.983587 | G46: =SUM(C46:F46) -> 75.534266
A47: + Funding surplus (row 21) | C47: =C21 -> 0 | D47: =D21 -> 0 | E47: =E21 -> 0 | F47: =F21 -> 0 | G47: =SUM(C47:F47) -> 0
A48: Closing cash | C48: =C45+C46+C47 -> 13.745393 | D48: =D45+D46+D47 -> 28.090599 | E48: =E45+E46+E47 -> 51.592779 | F48: =F45+F46+F47 -> 83.576366 | G48: =F48 -> 83.576366
A49: Equity Dilution
B50: Jun'26 A | C50: 2027 | D50: 2028 | E50: 2029 | F50: 2030 | G50: 2027–30
A51: Opening shares | C51: =B23 -> 271.855 | D51: =C23 -> 311.99028 | E51: =D23 -> 331.9794 | F51: =E23 -> 345.21938 | G51: =C51 -> 271.855
A52: Issue price ($/share) — derived (see row 63) | C52: =C79 -> 336.3624 | D52: =D79 -> 675.36735 | E52: =E79 -> 1019.6395 | F52: =F79 -> 1325.4685 | G52: =IF(G53=0,0,G20*1000/G53) -> 646.32378
A53: New shares (= equity ÷ issue price) | C53: =IF(C52=0,0,C20*1000/C52) -> 40.135283 | D53: =IF(D52=0,0,D20*1000/D52) -> 19.989122 | E53: =IF(E52=0,0,E20*1000/E52) -> 13.239974 | F53: =IF(F52=0,0,F20*1000/F52) -> 10.185078 | G53: =SUM(C53:F53) -> 83.549456
A54: Dilution in year | C54: =C23/C51-1 -> 0.14763489 | D54: =D23/D51-1 -> 0.064069693 | E54: =E23/E51-1 -> 0.039881914 | F54: =F23/F51-1 -> 0.029503204 | G54: =F23/C51-1 -> 0.30733095
A55: Estimated conversion premium | B55: 0.4
A56: Converts
B57: Jun'26 A | C57: 2027 | D57: 2028 | E57: 2029 | F57: 2030 | G57: 2027–30
A58: Conversion price of that year's converts | C58: =C52*(1+$B$55) -> 470.90736 | D58: =D52*(1+$B$55) -> 945.51429 | E58: =E52*(1+$B$55) -> 1427.4952 | F58: =F52*(1+$B$55) -> 1855.656 | G58: =IF(G59=0,0,G19*1000/G59) -> 600.68658
A59: Potential shares from that year's converts | C59: =IF(C58=0,0,C19*1000/C58) -> 10.981459 | D59: =IF(D58=0,0,D19*1000/D58) -> 3.1094189 | E59: =IF(E58=0,0,E19*1000/E58) -> 0.42688408 | F59: =IF(F58=0,0,F19*1000/F58) -> 0 | G59: =SUM(C59:F59) -> 14.517762
A60: Shares if every new convert converts | C60: =C23+SUM($C$59:C59) -> 322.97174 | D60: =D23+SUM($C$59:D59) -> 346.07028 | E60: =E23+SUM($C$59:E59) -> 359.73714 | F60: =F23+SUM($C$59:F59) -> 369.92222 | G60: =F60 -> 369.92222
A61: Cumulative dilution vs Jun-2026 actual | C61: =C60/$B$23-1 -> 0.18802944 | D61: =D60/$B$23-1 -> 0.27299583 | E61: =E60/$B$23-1 -> 0.32326844 | F61: =F60/$B$23-1 -> 0.36073355 | G61: =F61 -> 0.36073355
A63: Assumptions
A64: Equity slice (% of capex) | B64: 0.2
A65: Prepayments (% of capex) | B65: 0.45
A66: Total program capex ($B) | B66: 270
A67: EBITDA applied to capex (% of EBITDA) | B67: 0.15
A68: Secured / asset-backed cap (% of capex) — drawn first | B68: 0.25
A69: EV/EBITDA multiple (drives derived share price) | B69: 9.5
A70: Secured / asset-backed interest rate (%) | B70: 0.075
A71: Convertible note coupon (%) | B71: 0.01
A73: Valuation — share price derived from EBITDA × multiple
C74: 2027 | D74: 2028 | E74: 2029 | F74: 2030
A75: EBITDA | C75: =C9 -> 10.525 | D75: =D9 -> 25.4 | E75: =E9 -> 40.9375 | F75: =F9 -> 55.3125
A76: Enterprise value (EBITDA × multiple) | C76: =C75*$B$69 -> 99.9875 | D76: =D75*$B$69 -> 241.3 | E76: =E75*$B$69 -> 388.90625 | F76: =F75*$B$69 -> 525.46875
A77: Less: opening debt | C77: =C33 -> 8.5457 | D77: =D33 -> 30.59195 | E77: =E33 -> 50.40695 | F77: =F33 -> 67.891325
A78: Equity value (pre-money) | C78: =C76-C77 -> 91.4418 | D78: =D76-D77 -> 210.70805 | E78: =E76-E77 -> 338.4993 | F78: =F76-F77 -> 457.57743
A79: Derived share price (= equity value ÷ opening shares) | C79: =IF(C51=0,0,C78*1000/C51) -> 336.3624 | D79: =IF(D51=0,0,D78*1000/D51) -> 675.36735 | E79: =IF(E51=0,0,E78*1000/E51) -> 1019.6395 | F79: =IF(F51=0,0,F78*1000/F51) -> 1325.4685
A81: Capital structure today — actuals as of June 30, 2026
A82: Total debt ($B) — 100% convertible notes | B82: 8.5457
A83: of which secured / asset-backed debt | B83: 0
A84: Cash and cash equivalents ($B) | B84: 8.0421
A85: Shares issued and outstanding (M) | B85: 271.855
A86: Prefunded warrants issued ($B, Q1 2026) | B86: 2
A87: Deferred revenue — customer prepayments ($B) | B87: 5.9752
A88: Convertible principal issued to date ($B) | B88: 8.5
A89: 2026 guidance: revenue $3.0–3.4B, exit ARR $7–9B | B89: 9

Sheet Depreciation
A1: GPU Depreciation Schedule — straight-line, vintage-layered
A2: $ in billions unless specified; capex linked from Model row 11
A4: Assumptions
A5: GPU share of program capex (%) | B5: 0.64
A6: GPU useful life (years) | B6: 5
A7: Salvage value (% of cost) | B7: 0
A8: Tax rate (%) | B8: 0.22
A10: Capex & depreciable base | D10: 2027 | E10: 2028 | F10: 2029 | G10: 2030 | H10: 2031 | I10: 2032 | J10: 2033 | K10: 2034 | L10: 2035 | M10: 2036
A11: Total program capex | D11: ='Debt Equity'!C11 -> 67.5 | E11: ='Debt Equity'!D11 -> 67.5 | F11: ='Debt Equity'!E11 -> 67.5 | G11: ='Debt Equity'!F11 -> 67.5 | H11: 0 | I11: 0 | J11: 0 | K11: 0 | L11: 0 | M11: 0
A12: GPU capex (= total × GPU share) | D12: =D11*$B$5 -> 43.2 | E12: =E11*$B$5 -> 43.2 | F12: =F11*$B$5 -> 43.2 | G12: =G11*$B$5 -> 43.2 | H12: =H11*$B$5 -> 0 | I12: =I11*$B$5 -> 0 | J12: =J11*$B$5 -> 0 | K12: =K11*$B$5 -> 0 | ... M12: =M11*$B$5 -> 0
A13: Annual depreciation per vintage (= cost × (1−salvage) ÷ life) | D13: =IF($B$6=0,0,D12*(1-$B$7)/$B$6) -> 8.64 | E13: =IF($B$6=0,0,E12*(1-$B$7)/$B$6) -> 8.64 | F13: =IF($B$6=0,0,F12*(1-$B$7)/$B$6) -> 8.64 | G13: =IF($B$6=0,0,G12*(1-$B$7)/$B$6) -> 8.64 | H13: =IF($B$6=0,0,H12*(1-$B$7)/$B$6) -> 0 | I13: =IF($B$6=0,0,I12*(1-$B$7)/$B$6) -> 0 | J13: =IF($B$6=0,0,J12*(1-$B$7)/$B$6) -> 0 | K13: =IF($B$6=0,0,K12*(1-$B$7)/$B$6) -> 0 | ... M13: =IF($B$6=0,0,M12*(1-$B$7)/$B$6) -> 0
A15: Depreciation by capex vintage | B15: Vintage | C15: Annual D
A16: 2027 vintage | B16: =D$10 -> 2027 | C16: =D$13 -> 8.64 | D16: =IF(AND(D$10>=$B16,D$10<=$B16+$B$6-1),$C16,0) -> 8.64 | E16: =IF(AND(E$10>=$B16,E$10<=$B16+$B$6-1),$C16,0) -> 8.64 | F16: =IF(AND(F$10>=$B16,F$10<=$B16+$B$6-1),$C16,0) -> 8.64 | G16: =IF(AND(G$10>=$B16,G$10<=$B16+$B$6-1),$C16,0) -> 8.64 | H16: =IF(AND(H$10>=$B16,H$10<=$B16+$B$6-1),$C16,0) -> 8.64 | I16: =IF(AND(I$10>=$B16,I$10<=$B16+$B$6-1),$C16,0) -> 0 | J16: =IF(AND(J$10>=$B16,J$10<=$B16+$B$6-1),$C16,0) -> 0 | K16: =IF(AND(K$10>=$B16,K$10<=$B16+$B$6-1),$C16,0) -> 0 | ... M16: =IF(AND(M$10>=$B16,M$10<=$B16+$B$6-1),$C16,0) -> 0
A17: 2028 vintage | B17: =E$10 -> 2028 | C17: =E$13 -> 8.64 | D17: =IF(AND(D$10>=$B17,D$10<=$B17+$B$6-1),$C17,0) -> 0 | E17: =IF(AND(E$10>=$B17,E$10<=$B17+$B$6-1),$C17,0) -> 8.64 | F17: =IF(AND(F$10>=$B17,F$10<=$B17+$B$6-1),$C17,0) -> 8.64 | G17: =IF(AND(G$10>=$B17,G$10<=$B17+$B$6-1),$C17,0) -> 8.64 | H17: =IF(AND(H$10>=$B17,H$10<=$B17+$B$6-1),$C17,0) -> 8.64 | I17: =IF(AND(I$10>=$B17,I$10<=$B17+$B$6-1),$C17,0) -> 8.64 | J17: =IF(AND(J$10>=$B17,J$10<=$B17+$B$6-1),$C17,0) -> 0 | K17: =IF(AND(K$10>=$B17,K$10<=$B17+$B$6-1),$C17,0) -> 0 | ... M17: =IF(AND(M$10>=$B17,M$10<=$B17+$B$6-1),$C17,0) -> 0
A18: 2029 vintage | B18: =F$10 -> 2029 | C18: =F$13 -> 8.64 | D18: =IF(AND(D$10>=$B18,D$10<=$B18+$B$6-1),$C18,0) -> 0 | E18: =IF(AND(E$10>=$B18,E$10<=$B18+$B$6-1),$C18,0) -> 0 | F18: =IF(AND(F$10>=$B18,F$10<=$B18+$B$6-1),$C18,0) -> 8.64 | G18: =IF(AND(G$10>=$B18,G$10<=$B18+$B$6-1),$C18,0) -> 8.64 | H18: =IF(AND(H$10>=$B18,H$10<=$B18+$B$6-1),$C18,0) -> 8.64 | I18: =IF(AND(I$10>=$B18,I$10<=$B18+$B$6-1),$C18,0) -> 8.64 | J18: =IF(AND(J$10>=$B18,J$10<=$B18+$B$6-1),$C18,0) -> 8.64 | K18: =IF(AND(K$10>=$B18,K$10<=$B18+$B$6-1),$C18,0) -> 0 | ... M18: =IF(AND(M$10>=$B18,M$10<=$B18+$B$6-1),$C18,0) -> 0
A19: 2030 vintage | B19: =G$10 -> 2030 | C19: =G$13 -> 8.64 | D19: =IF(AND(D$10>=$B19,D$10<=$B19+$B$6-1),$C19,0) -> 0 | E19: =IF(AND(E$10>=$B19,E$10<=$B19+$B$6-1),$C19,0) -> 0 | F19: =IF(AND(F$10>=$B19,F$10<=$B19+$B$6-1),$C19,0) -> 0 | G19: =IF(AND(G$10>=$B19,G$10<=$B19+$B$6-1),$C19,0) -> 8.64 | H19: =IF(AND(H$10>=$B19,H$10<=$B19+$B$6-1),$C19,0) -> 8.64 | I19: =IF(AND(I$10>=$B19,I$10<=$B19+$B$6-1),$C19,0) -> 8.64 | J19: =IF(AND(J$10>=$B19,J$10<=$B19+$B$6-1),$C19,0) -> 8.64 | K19: =IF(AND(K$10>=$B19,K$10<=$B19+$B$6-1),$C19,0) -> 8.64 | ... M19: =IF(AND(M$10>=$B19,M$10<=$B19+$B$6-1),$C19,0) -> 0
A21: Total GPU depreciation | D21: =SUM(D16:D19) -> 8.64 | E21: =SUM(E16:E19) -> 17.28 | F21: =SUM(F16:F19) -> 25.92 | G21: =SUM(G16:G19) -> 34.56 | H21: =SUM(H16:H19) -> 34.56 | I21: =SUM(I16:I19) -> 25.92 | J21: =SUM(J16:J19) -> 17.28 | K21: =SUM(K16:K19) -> 8.64 | ... M21: =SUM(M16:M19) -> 0
A22: Cumulative depreciation | D22: =SUM($D$21:D21) -> 8.64 | E22: =SUM($D$21:E21) -> 25.92 | F22: =SUM($D$21:F21) -> 51.84 | G22: =SUM($D$21:G21) -> 86.4 | H22: =SUM($D$21:H21) -> 120.96 | I22: =SUM($D$21:I21) -> 146.88 | J22: =SUM($D$21:J21) -> 164.16 | K22: =SUM($D$21:K21) -> 172.8 | ... M22: =SUM($D$21:M21) -> 172.8
A24: PP&E rollforward
A25: Gross GPU PP&E (closing) | D25: =SUM($D$12:D12) -> 43.2 | E25: =SUM($D$12:E12) -> 86.4 | F25: =SUM($D$12:F12) -> 129.6 | G25: =SUM($D$12:G12) -> 172.8 | H25: =SUM($D$12:H12) -> 172.8 | I25: =SUM($D$12:I12) -> 172.8 | J25: =SUM($D$12:J12) -> 172.8 | K25: =SUM($D$12:K12) -> 172.8 | ... M25: =SUM($D$12:M12) -> 172.8
A26: Less: accumulated depreciation | D26: =-D22 -> -8.64 | E26: =-E22 -> -25.92 | F26: =-F22 -> -51.84 | G26: =-G22 -> -86.4 | H26: =-H22 -> -120.96 | I26: =-I22 -> -146.88 | J26: =-J22 -> -164.16 | K26: =-K22 -> -172.8 | ... M26: =-M22 -> -172.8
A27: Net book value (closing) | D27: =D25+D26 -> 34.56 | E27: =E25+E26 -> 60.48 | F27: =F25+F26 -> 77.76 | G27: =G25+G26 -> 86.4 | H27: =H25+H26 -> 51.84 | I27: =I25+I26 -> 25.92 | J27: =J25+J26 -> 8.64 | K27: =K25+K26 -> 0 | ... M27: =M25+M26 -> 0
A29: Check: total depreciation over life − depreciable cost (must be 0) | D29: =SUM(D21:M21)-SUM(D12:M12)*(1-$B$7) -> 0
A31: Memo: EBITDA | D31: ='Debt Equity'!C9 -> 10.525 | E31: ='Debt Equity'!D9 -> 25.4 | F31: ='Debt Equity'!E9 -> 40.9375 | G31: ='Debt Equity'!F9 -> 55.3125
A32: Memo: EBIT (= EBITDA − GPU depreciation) | D32: =D31-D21 -> 1.885 | E32: =E31-E21 -> 8.12 | F32: =F31-F21 -> 15.0175 | G32: =G31-G21 -> 20.7525
A33: Less: cash interest (Debt Equity row 40) | D33: =-'Debt Equity'!C40 -> -0.085457 | E33: =-'Debt Equity'!D40 -> -1.4027945 | F33: =-'Debt Equity'!E40 -> -2.6978195 | G33: =-'Debt Equity'!F40 -> -3.9695382
A34: Earnings before tax (= EBIT − interest) | D34: =D32+D33 -> 1.799543 | E34: =E32+E33 -> 6.7172055 | F34: =F32+F33 -> 12.31968 | G34: =G32+G33 -> 16.782962
A35: Less: tax (= EBT × tax rate, floored at zero) | D35: =-MAX(0,D34)*$B$8 -> -0.39589946 | E35: =-MAX(0,E34)*$B$8 -> -1.4777852 | F35: =-MAX(0,F34)*$B$8 -> -2.7103297 | G35: =-MAX(0,G34)*$B$8 -> -3.6922516
A36: Earnings after tax | D36: =D34+D35 -> 1.4036435 | E36: =E34+E35 -> 5.2394203 | F36: =F34+F35 -> 9.6093508 | G36: =G34+G35 -> 13.09071
A38: EPS: | D38: =D36/0.3522 -> 3.9853593 | E38: =E36/0.3522 -> 14.876264 | F38: =F36/0.3522 -> 27.28379 | G38: =G36/0.3522 -> 37.168399
A39: Multiple | B39: 20 | D39: =$B$39*D38 -> 79.707186 | E39: =$B$39*E38 -> 297.52529 | F39: =$B$39*F38 -> 545.6758 | G39: =$B$39*G38 -> 743.36798
